m/commands/read/__init__.py
m/commands/read/impl.py
mm_read-0.0.4.dist-info/METADATA
mm_read-0.0.4.dist-info/WHEEL
mm_read-0.0.4.dist-info/entry_points.txt
mm_read/extract.py
mm_read/fetch.py
mm_read/parse.py
mm_read-0.0.4.dist-info/RECORD
