Metadata-Version: 2.1
Name: mm-read
Version: 0.0.4
Summary: Readability utilities for personal use
Requires-Python: >=3.12
Requires-Dist: html2text2~=1.0
Requires-Dist: mistune~=3.1.4
Requires-Dist: niquests~=3.11
Requires-Dist: python-readability~=1.0.0rc0
